{
    "wazas":[
        {
            "id": 1,
            "waza":"レジェンド(飛行機～はやて中皿～天中殺)",
            "favoriteSum":4,
            "level":1,
            "makeSum":10,
            "url":"https://www.youtube.com/watch?v=WqiUiVnxghU"
        },
        {
            "id": 2,
            "waza":"吊るしとめけん〜持ち替え〜はねけん",
            "favoriteSum":0,
            "level":1,
            "makeSum":0,
            "url":"https://www.youtube.com/watch?v=VnN7XVamkQQ"
        },
        {
            "id": 3,
            "waza":"ふりけん～世界一周～地球回し",
            "favoriteSum":0,
            "level":1,
            "makeSum":0,
            "url":"https://www.youtube.com/watch?v=v359dNUe-Xw"
        },
        {
            "id": 4,
            "waza":"灯台〜灯台とんぼ返り〜逆落とし",
            "favoriteSum":0,
            "level":2,
            "makeSum":0,
            "url":"https://www.youtube.com/watch?v=8yKssczWB6k"
        },
        {
            "id": 5,
            "waza":"空中ブランコ～天中殺～地獄回し",
            "favoriteSum":0,
            "level":2,
            "makeSum":0,
            "url":"https://www.youtube.com/watch?v=7qFGLJkJXNA"
        },
        {
            "id": 6,
            "waza":"月に落ちたUFO（月面～逆落とし～UFO",
            "favoriteSum":0,
            "level":2,
            "makeSum":0,
            "url":"https://www.youtube.com/watch?v=z8W9Y5Xv414"
        },
        {
            "id": 7,
            "waza":"天中殺〜倒立〜持ち替えけん",
            "favoriteSum":0,
            "level":2,
            "makeSum":0,
            "url":"https://www.youtube.com/watch?v=PH3gzeKxzGM"
        },
        {
            "id": 8,
            "waza":"フリップ大皿〜中皿〜遠心力〜持ち替え中皿〜天中殺",
            "favoriteSum":0,
            "level":2,
            "makeSum":0,
            "url":"https://www.youtube.com/watch?v=ZeCAlhmeUzg"
        },
        {
            "id": 9,
            "waza":"裏けん先〜飛竜上りけん",
            "favoriteSum":0,
            "level":2,
            "makeSum":0,
            "url":"https://www.youtube.com/watch?v=D4Wh6gk0Rr4"
        },
        {
            "id": 10,
            "waza":"吊るし灯台〜すくいけん〜中皿〜けん",
            "favoriteSum":0,
            "level":2,
            "makeSum":0,
            "url":"https://www.youtube.com/watch?v=PBg1-TuQmVM"
        },
        {
            "id": 11,
            "waza":"忍者(日本一周～持ち替え～持ち替え中皿～天中殺)",
            "favoriteSum":0,
            "level":2,
            "makeSum":0,
            "url":"https://www.youtube.com/watch?v=4bJk4m4KaUQ"
        },
        {
            "id": 12,
            "waza":"くるくる月面〜逆落とし〜ゼロはねけん",
            "favoriteSum":0,
            "level":2,
            "makeSum":0,
            "url":"https://www.youtube.com/watch?v=EPA75im7Tg8"
        },
        {
            "id": 13,
            "waza":"1回転飛行機〜1.5とめけん〜ワールウィンド",
            "favoriteSum":0,
            "level":4,
            "makeSum":0,
            "url":"https://www.youtube.com/watch?v=-BwVvySpDBI"
        },
        {
            "id": 14,
            "waza":"うぐいす〜こっくり〜谷渡り〜回転けん",
            "favoriteSum":0,
            "level":2,
            "makeSum":0,
            "url":"https://www.youtube.com/watch?v=lyoqpLUjelI"
        },
        {
            "id": 15,
            "waza":"飛行機〜倒立〜天中殺",
            "favoriteSum":0,
            "level":2,
            "makeSum":0,
            "url":"https://www.youtube.com/watch?v=8RncbQnTSZY"
        },
        {
            "id": 16,
            "waza":"前振りろうそく〜ろうそく返し〜地球回し",
            "favoriteSum":0,
            "level":2,
            "makeSum":0,
            "url":"https://www.youtube.com/watch?v=hEYgl5ttQfI"
        },
        {
            "id": 17,
            "waza":"1回転灯台〜月面着陸〜1回転逆落とし",
            "favoriteSum":0,
            "level":3,
            "makeSum":0,
            "url":"https://www.youtube.com/watch?v=bRytABu-LsE"
        },
        {
            "id": 18,
            "waza":"宇宙遊泳〜灯台インスタけん",
            "favoriteSum":0,
            "level":4,
            "makeSum":0,
            "url":"https://www.youtube.com/watch?v=HR99C1e2MjE"
        },
        {
            "id": 19,
            "waza":"中皿フリップ中皿〜天中殺〜バックスルー天中",
            "favoriteSum":0,
            "level":3,
            "makeSum":0,
            "url":"https://www.youtube.com/watch?v=5m0zAMlgYZ8"
        },
        {
            "id": 20,
            "waza":"裏月面〜裏倒立〜裏逆落とし",
            "favoriteSum":0,
            "level":3,
            "makeSum":0,
            "url":"https://www.youtube.com/watch?v=7H3IaQ2KyIE"
        },
        {
            "id": 21,
            "waza":"月についた侍(月面～竹馬～天中殺)",
            "favoriteSum":0,
            "level":3,
            "makeSum":0,
            "url":"https://www.youtube.com/watch?v=NuGKoA0oAB0"
        },
        {
            "id": 22,
            "waza":"風車ふりけん〜裏地球回し〜風車地球回し",
            "favoriteSum":0,
            "level":3,
            "makeSum":0,
            "url":"https://www.youtube.com/watch?v=w-lTvmgvemI"
        },
        {
            "id": 23,
            "waza":"ジャグ大皿〜ターンテーブル〜大皿返し",
            "favoriteSum":0,
            "level":3,
            "makeSum":0,
            "url":"https://www.youtube.com/watch?v=40lLRgPYzZw"
        },
        {
            "id": 24,
            "waza":"ポップコーン〜バルタン星人〜小指姫",
            "favoriteSum":0,
            "level":2,
            "makeSum":0,
            "url":"https://www.youtube.com/watch?v=CWSqTnOlKac"
        },
        {
            "id": 25,
            "waza":"中皿遠心力灯台〜すくいけんファストハンド",
            "favoriteSum":0,
            "level":3,
            "makeSum":0,
            "url":"https://www.youtube.com/watch?v=vfUdSaEa4JY"
        },
        {
            "id": 26,
            "waza":"振りうぐいす〜回転うぐいす〜回転けん",
            "favoriteSum":0,
            "level":3,
            "makeSum":0,
            "url":"https://www.youtube.com/watch?v=FQwrqu1mwSE"
        },
        {
            "id": 27,
            "waza":"飛行機〜はやてろうそく〜天中殺",
            "favoriteSum":0,
            "level":2,
            "makeSum":0,
            "url":"https://www.youtube.com/watch?v=519JvziB1es"
        },
        {
            "id": 28,
            "waza":"天中ファストハンド〜はねけん天中〜スクリュー",
            "favoriteSum":0,
            "level":3,
            "makeSum":0,
            "url":"https://www.youtube.com/watch?v=SweslsH6_Eg"
        },
        {
            "id": 29,
            "waza":"タップ中皿〜倒立〜持ち替えけん",
            "favoriteSum":0,
            "level":3,
            "makeSum":0,
            "url":"https://www.youtube.com/watch?v=_Xz2q8neAMI"
        },
        {
            "id": 30,
            "waza":"ジャグ天中〜灯台インスタ天中〜ジャグ天中",
            "favoriteSum":0,
            "level":5,
            "makeSum":0,
            "url":"https://www.youtube.com/watch?v=npOLB2CWjP0"
        },
        {
            "id": 31,
            "waza":"横バィーン〜持ち替え中皿〜ペンギンけん",
            "favoriteSum":0,
            "level":2,
            "makeSum":0,
            "url":"https://www.youtube.com/watch?v=XJgN5R_Lb0o"
        },
        {
            "id": 32,
            "waza":"居合い鶯〜谷渡り〜裏回転けん",
            "favoriteSum":0,
            "level":3,
            "makeSum":0,
            "url":"https://www.youtube.com/watch?v=8th4Rr1kuWY"
        },
        {
            "id": 33,
            "waza":"アンダーバード〜逆落とし〜はねけん",
            "favoriteSum":0,
            "level":2,
            "makeSum":0,
            "url":"https://www.youtube.com/watch?v=WdbE2JSmitw"
        },
        {
            "id": 34,
            "waza":"吊るし天中〜ガンマン〜地球回し",
            "favoriteSum":0,
            "level":3,
            "makeSum":0,
            "url":"https://www.youtube.com/watch?v=ekfiPlkp8kY"
        },
        {
            "id": 35,
            "waza":"ずーまキャッチ〜中皿フリップ中皿〜逆落とし",
            "favoriteSum":0,
            "level":3,
            "makeSum":0,
            "url":"https://www.youtube.com/watch?v=pN_DTDz8Cxo"
        },
        {
            "id": 36,
            "waza":"タップ灯台〜一回転逆落とし〜1.5とめけん",
            "favoriteSum":0,
            "level":4,
            "makeSum":0,
            "url":"https://www.youtube.com/watch?v=M6oIjkJr4bs"
        },
        {
            "id": 37,
            "waza":"すくいけん〜無回転灯台〜すくいけん",
            "favoriteSum":0,
            "level":3,
            "makeSum":0,
            "url":"https://www.youtube.com/watch?v=5qqLJU4oMzA"
        },
        {
            "id": 38,
            "waza":"月面〜月面とんぼ返り〜逆落としファストハンド",
            "favoriteSum":0,
            "level":3,
            "makeSum":0,
            "url":"https://www.youtube.com/watch?v=9BzEXbXmCe8"
        },
        {
            "id": 39,
            "waza":"魔女のスープ〜中皿よそい〜いただきます",
            "favoriteSum":0,
            "level":1,
            "makeSum":0,
            "url":"https://www.youtube.com/watch?v=kAwPvawaPhQ"
        },
        {
            "id": 40,
            "waza":"宇宙遊泳一回転灯台〜フリップ灯台〜タップイン",
            "favoriteSum":0,
            "level":4,
            "makeSum":0,
            "url":"https://www.youtube.com/watch?v=Z_Bq3opgb_E"
        },
        {
            "id": 41,
            "waza":"一回転飛行機〜裏はねけん〜はねけん",
            "favoriteSum":0,
            "level":3,
            "makeSum":0,
            "url":"https://www.youtube.com/watch?v=ijsKuYgMNvs"
        },
        {
            "id": 42,
            "waza":"中皿極意〜極意渡り〜回転けん",
            "favoriteSum":0,
            "level":3,
            "makeSum":0,
            "url":"https://www.youtube.com/watch?v=SGz4iDnO60M"
        },
        {
            "id": 43,
            "waza":"こねくり〜Sweets スペシャル〜天中殺",
            "favoriteSum":0,
            "level":3,
            "makeSum":0,
            "url":"https://www.youtube.com/watch?v=O-4zIxmNwDY"
        },
        {
            "id": 44,
            "waza":"空中ブランコ～もしかめ3回～野球",
            "favoriteSum":0,
            "level":1,
            "makeSum":0,
            "url":"https://www.youtube.com/watch?v=dwmJgK5xgvg"
        },
        {
            "id": 45,
            "waza":"天中ファストハンド〜持ち替えペンギンけん",
            "favoriteSum":0,
            "level":2,
            "makeSum":0,
            "url":"https://www.youtube.com/watch?v=jX8we347rhQ"
        },
        {
            "id": 46,
            "waza":"とめけん～竹とんぼ～持ち替え",
            "favoriteSum":0,
            "level":1,
            "makeSum":0,
            "url":"https://www.youtube.com/watch?v=Rn0nq0Oef7I"
        },
        {
            "id": 47,
            "waza":"竹馬～倒立～持ち替えけん",
            "favoriteSum":0,
            "level":2,
            "makeSum":0,
            "url":"https://www.youtube.com/watch?v=LsTuGvAcCLw"
        },
        {
            "id": 48,
            "waza":"除夜の鐘～ご挨拶～お年玉",
            "favoriteSum":0,
            "level":1,
            "makeSum":0,
            "url":"https://www.youtube.com/watch?v=4_Rkf7u4j9g"
        },
        {
            "id": 49,
            "waza":"フリップ灯台〜インスタとんぼ返り〜タップ1回転逆落とし",
            "favoriteSum":0,
            "level":4,
            "makeSum":0,
            "url":"https://www.youtube.com/watch?v=jgpt6_pu_Ms"
        },
        {
            "id": 50,
            "waza":"おみこし〜おすべり〜天中殺",
            "favoriteSum":0,
            "level":1,
            "makeSum":0,
            "url":"https://www.youtube.com/watch?v=gadceIgTloY"
        },
        {
            "id": 51,
            "waza":"ペンギン中皿〜大皿〜けん",
            "favoriteSum":0,
            "level":1,
            "makeSum":0,
            "url":"https://www.youtube.com/watch?v=UVmeiOnDoEU"
        },
        {
            "id": 52,
            "waza":"振り小皿鶯〜こっくり〜ペンギンけん",
            "favoriteSum":0,
            "level":3,
            "makeSum":0,
            "url":"https://www.youtube.com/watch?v=xhx9iBKvGJs"
        },
        {
            "id": 53,
            "waza":"けん先滑り〜裏けんさき滑り",
            "favoriteSum":0,
            "level":3,
            "makeSum":0,
            "url":"https://www.youtube.com/watch?v=P3WvzhSxHnk"
        },
        {
            "id": 54,
            "waza":"一回転灯台～中皿～倒立～すくいけん",
            "favoriteSum":0,
            "level":2,
            "makeSum":0,
            "url":"https://www.youtube.com/watch?v=Mpzslgx2DJs"
        },
        {
            "id": 55,
            "waza":"ふりけん〜ふりけん〜地球回し",
            "favoriteSum":0,
            "level":2,
            "makeSum":0,
            "url":"https://www.youtube.com/watch?v=dNJriP9e1SU"
        },
        {
            "id": 56,
            "waza":"風車大皿〜ターンテーブル〜けん",
            "favoriteSum":0,
            "level":2,
            "makeSum":0,
            "url":"https://www.youtube.com/watch?v=H-atSmk7pIQ"
        },
        {
            "id": 57,
            "waza":"飛行機〜うずしお空中ブランコ",
            "favoriteSum":0,
            "level":2,
            "makeSum":0,
            "url":"https://www.youtube.com/watch?v=spn_3KrDJ-4"
        },
        {
            "id": 58,
            "waza":"フリップとめけん〜フリップ〜Wフリップ",
            "favoriteSum":0,
            "level":4,
            "makeSum":0,
            "url":"https://www.youtube.com/watch?v=TDmxaVsHUU4"
        },
        {
            "id": 59,
            "waza":"大皿〜持ち替え中皿〜小皿〜持ち替え中皿〜持ち替え中皿〜天中殺",
            "favoriteSum":0,
            "level":2,
            "makeSum":0,
            "url":"https://www.youtube.com/watch?v=zhQKeR6mIf8"
        },
        {
            "id": 60,
            "waza":"Wフリップ〜2ジャグ〜2回転逆落とし",
            "favoriteSum":0,
            "level":5,
            "makeSum":0,
            "url":"https://www.youtube.com/watch?v=tVyhT0X1lV4"
        },
        {
            "id": 61,
            "waza":"すくいけん〜バックスルーはやて中皿〜ゴースト逆落とし",
            "favoriteSum":0,
            "level":3,
            "makeSum":0,
            "url":"https://www.youtube.com/watch?v=tEyug4Q8M_w"
        },
        {
            "id": 62,
            "waza":"竹馬〜逆落としファストハンド〜一回転逆落とし",
            "favoriteSum":0,
            "level":3,
            "makeSum":0,
            "url":"https://www.youtube.com/watch?v=kzSkhbpC3sg"
        },
        {
            "id": 63,
            "waza":"ろうそく〜リフティング小皿〜ろうそく一周",
            "favoriteSum":0,
            "level":2,
            "makeSum":0,
            "url":"https://www.youtube.com/watch?v=R0O6E0zwYDU"
        },
        {
            "id": 64,
            "waza":"デンマーク一周(大皿～フリップ小皿～逆落とし～はやて中皿～天中殺)",
            "favoriteSum":0,
            "level":3,
            "makeSum":0,
            "url":"https://www.youtube.com/watch?v=G_cZ10ZvSjA"
        },
        {
            "id": 65,
            "waza":"ふりけん〜ゴースト灯台〜持ち替えけん",
            "favoriteSum":0,
            "level":3,
            "makeSum":0,
            "url":"https://www.youtube.com/watch?v=xZgi36PinCU"
        },
        {
            "id": 66,
            "waza":"大皿〜Bダッシュ〜つばめ返し",
            "favoriteSum":0,
            "level":1,
            "makeSum":0,
            "url":"https://www.youtube.com/watch?v=XcfEAkjwVFA"
        },
        {
            "id": 67,
            "waza":"裏振りうぐいす〜うぐいすの谷渡り〜天中殺",
            "favoriteSum":0,
            "level":3,
            "makeSum":0,
            "url":"https://www.youtube.com/watch?v=9a605XfB540"
        },
        {
            "id": 68,
            "waza":"フリップ灯台〜１回転逆落とし〜はねけん",
            "favoriteSum":0,
            "level":3,
            "makeSum":0,
            "url":"https://www.youtube.com/watch?v=VASzt4UkbDU"
        },
        {
            "id": 69,
            "waza":"中皿〜月面〜逆落とし",
            "favoriteSum":0,
            "level":2,
            "makeSum":0,
            "url":"https://www.youtube.com/watch?v=9ul3U3c9rAE"
        },
        {
            "id": 70,
            "waza":"アンダーバード〜天中ファストハンド〜2回転はねけん",
            "favoriteSum":0,
            "level":3,
            "makeSum":0,
            "url":"https://www.youtube.com/watch?v=YCusZHl7_XE"
        },
        {
            "id": 71,
            "waza":"飛行機〜持ち替え〜地球回し",
            "favoriteSum":0,
            "level":1,
            "makeSum":0,
            "url":"https://www.youtube.com/watch?v=ema8ssMX8Rc"
        },
        {
            "id": 72,
            "waza":"マテオチャンス(フリップジャグフリップジャグけん)",
            "favoriteSum":0,
            "level":5,
            "makeSum":0,
            "url":"https://www.youtube.com/watch?v=WVC8xF0ZhVM"
        },
        {
            "id": 73,
            "waza":"１回転飛行機〜倒立〜１回転持ち替えけん",
            "favoriteSum":0,
            "level":3,
            "makeSum":0,
            "url":"https://www.youtube.com/watch?v=FIrJDqdEst0"
        },
        {
            "id": 74,
            "waza":"天中殺〜中皿〜天中殺〜地獄回し",
            "favoriteSum":0,
            "level":2,
            "makeSum":0,
            "url":"https://www.youtube.com/watch?v=sNmhJSHWMAg"
        },
        {
            "id": 75,
            "waza":"竹馬〜けん〜裏地球回し",
            "favoriteSum":0,
            "level":2,
            "makeSum":0,
            "url":"https://www.youtube.com/watch?v=hPPxUjKkhmU"
        },
        {
            "id": 76,
            "waza":"月面〜月面とんぼ返り〜一回転逆落とし",
            "favoriteSum":0,
            "level":2,
            "makeSum":0,
            "url":"https://www.youtube.com/watch?v=l16ybnaAfyY"
        },
        {
            "id": 77,
            "waza":"ジャグ大皿〜うぐいす〜すくいけん",
            "favoriteSum":0,
            "level":3,
            "makeSum":0,
            "url":"https://www.youtube.com/watch?v=THkkA13-LyU"
        },
        {
            "id": 78,
            "waza":"中皿極意〜UFO〜はねけん",
            "favoriteSum":0,
            "level":4,
            "makeSum":0,
            "url":"https://www.youtube.com/watch?v=eyJl9nlT0rA"
        },
        {
            "id": 79,
            "waza":"飛龍〜持ち替え中皿〜天中",
            "favoriteSum":0,
            "level":2,
            "makeSum":0,
            "url":"https://www.youtube.com/watch?v=nDVdLeKid0E"
        },
        {
            "id": 80,
            "waza":"裏世界一周(小皿月面～月面～倒立～逆落とし)",
            "favoriteSum":0,
            "level":3,
            "makeSum":0,
            "url":"https://www.youtube.com/watch?v=XBq_oKPbbvA"
        },
        {
            "id": 81,
            "waza":"金魚すくい〜持ち替えろうそく〜ろうそく返し",
            "favoriteSum":0,
            "level":2,
            "makeSum":0,
            "url":"https://www.youtube.com/watch?v=Aeyg2R_JpXM"
        },
        {
            "id": 82,
            "waza":"裏月面〜１回転クッション月面〜裏逆落とし",
            "favoriteSum":0,
            "level":4,
            "makeSum":0,
            "url":"https://www.youtube.com/watch?v=WMUjtTIUhdg"
        },
        {
            "id": 83,
            "waza":"ブリッジ〜エレベーターすくいけん〜持ち替え",
            "favoriteSum":0,
            "level":1,
            "makeSum":0,
            "url":"https://www.youtube.com/watch?v=e9w1sC1BeKU"
        },
        {
            "id": 84,
            "waza":"てんとう虫〜つばめ返し〜けん",
            "favoriteSum":0,
            "level":2,
            "makeSum":0,
            "url":"https://www.youtube.com/watch?v=cO6TpupjL5k"
        },
        {
            "id": 85,
            "waza":"被せ灯台〜バンジーゴースト灯台〜すくいけんペンギンファスト",
            "favoriteSum":0,
            "level":4,
            "makeSum":0,
            "url":"https://www.youtube.com/watch?v=MhH3VqQdmGQ"
        },
        {
            "id": 86,
            "waza":"裏飛行機〜１回転月面〜１回転持ち替えけん",
            "favoriteSum":0,
            "level":3,
            "makeSum":0,
            "url":"https://www.youtube.com/watch?v=jhk2S7DVpDU"
        },
        {
            "id": 87,
            "waza":"犬のしつけ",
            "favoriteSum":0,
            "level":1,
            "makeSum":0,
            "url":"https://www.youtube.com/watch?v=_OwcjGCSVqU"
        },
        {
            "id": 88,
            "waza":"スワップ飛行機〜1.5うぐいす〜インワードけん",
            "favoriteSum":0,
            "level":5,
            "makeSum":0,
            "url":"https://www.youtube.com/watch?v=iMPA-GYDa1k"
        },
        {
            "id": 89,
            "waza":"リフティング大皿〜遠心力裏月〜天中殺",
            "favoriteSum":0,
            "level":4,
            "makeSum":0,
            "url":"https://www.youtube.com/watch?v=HM6ciKz8HpQ"
        },
        {
            "id": 90,
            "waza":"フリップ大皿〜インワード大皿〜フリップけん",
            "favoriteSum":0,
            "level":3,
            "makeSum":0,
            "url":"https://www.youtube.com/watch?v=JL46w5biWlg"
        },
        {
            "id": 91,
            "waza":"飛行機～ダーティーフィンガー灯台～1回転逆落とし",
            "favoriteSum":0,
            "level":3,
            "makeSum":0,
            "url":"https://www.youtube.com/watch?v=14KTzT6VEfU"
        },
        {
            "id": 92,
            "waza":"すくいけん〜トーキル〜１回転タップすくいけん",
            "favoriteSum":0,
            "level":4,
            "makeSum":0,
            "url":"https://www.youtube.com/watch?v=y0wqw7SOV2Q"
        },
        {
            "id": 93,
            "waza":"月面〜裏インスタ月面トンボ返り〜逆落としファストハンド",
            "favoriteSum":0,
            "level":4,
            "makeSum":0,
            "url":"https://www.youtube.com/watch?v=pUHtIBN7Tcg"
        },
        {
            "id": 94,
            "waza":"たこ焼き一丁〜中皿〜持ち灯台",
            "favoriteSum":0,
            "level":1,
            "makeSum":0,
            "url":"https://www.youtube.com/watch?v=JvZKHqeygNw"
        },
        {
            "id": 95,
            "waza":"銀河系一周",
            "favoriteSum":0,
            "level":4,
            "makeSum":0,
            "url":"https://www.youtube.com/watch?v=WdALnlME8QM"
        },
        {
            "id": 96,
            "waza":"ジャグけん〜ワールウィンド〜地球回し",
            "favoriteSum":0,
            "level":4,
            "makeSum":0,
            "url":"https://www.youtube.com/watch?v=R1Oi3FBSuaE"
        },
        {
            "id": 97,
            "waza":"中皿〜天中殺〜地獄ぐるまファストハンド",
            "favoriteSum":0,
            "level":3,
            "makeSum":0,
            "url":"https://www.youtube.com/watch?v=dbXzekMGoyA"
        },
        {
            "id": 98,
            "waza":"2回転大皿〜インワード持ち替え中皿〜逆落とし",
            "favoriteSum":0,
            "level":4,
            "makeSum":0,
            "url":"https://www.youtube.com/watch?v=L4zvbMMa9dw"
        },
        {
            "id": 99,
            "waza":"3回転フリップ灯台〜3ジャグけん〜3回転ワールウィンド",
            "favoriteSum":0,
            "level":5,
            "makeSum":0,
            "url":"https://www.youtube.com/watch?v=y7O6EL6vEqY"
        },
        {
            "id": 100,
            "waza":"レジェンド〜持ち替え〜YANK",
            "favoriteSum":0,
            "level":3,
            "makeSum":0,
            "url":"https://www.youtube.com/watch?v=nVPcXhjFxHs"
        },
        {
            "id": 101,
            "waza":"村一周",
            "favoriteSum":0,
            "level":1,
            "makeSum":0,
            "url":"https://www.youtube.com/watch?v=C6PqvKCRa1o"
        },
        {
            "id": 102,
            "waza":"ろうそく〜フリップ中皿〜天中",
            "favoriteSum":0,
            "level":2,
            "makeSum":0,
            "url":"https://www.youtube.com/watch?v=loU-DepRZ40"
        },
        {
            "id": 103,
            "waza":"竹馬〜スイッチ天中〜両手地獄回し",
            "favoriteSum":0,
            "level":3,
            "makeSum":0,
            "url":"https://www.youtube.com/watch?v=_uQ56UCCVYE"
        },
        {
            "id": 104,
            "waza":"飛行機〜クッション裏月〜インスタ逆落とし",
            "favoriteSum":0,
            "level":4,
            "makeSum":0,
            "url":"https://www.youtube.com/watch?v=ib8Rv481ujE"
        },
        {
            "id": 105,
            "waza":"ピルエット〜こま〜地球回し",
            "favoriteSum":0,
            "level":1,
            "makeSum":0,
            "url":"https://www.youtube.com/watch?v=v6DVRA8R0FA"
        },
        {
            "id": 106,
            "waza":"風車大皿〜うぐいす〜谷渡り〜回転けん",
            "favoriteSum":0,
            "level":3,
            "makeSum":0,
            "url":"https://www.youtube.com/watch?v=aH3KHgsTV4Y"
        },
        {
            "id": 107,
            "waza":"飛行機〜無回転竹馬〜一回転逆落とし",
            "favoriteSum":0,
            "level":3,
            "makeSum":0,
            "url":"https://www.youtube.com/watch?v=8mdQt_1BGEw"
        },
        {
            "id": 108,
            "waza":"振り小皿うぐいす〜倒立〜持ち替えけん",
            "favoriteSum":0,
            "level":3,
            "makeSum":0,
            "url":"https://www.youtube.com/watch?v=ytFIf7WNc94"
        },
        {
            "id": 109,
            "waza":"イチロー",
            "favoriteSum":0,
            "level":1,
            "makeSum":0,
            "url":"https://www.youtube.com/watch?v=fg6gyDLMCZ4"
        },
        {
            "id": 110,
            "waza":"飛行機〜はねけん月面180裏月〜イン",
            "favoriteSum":0,
            "level":4,
            "makeSum":0,
            "url":"https://www.youtube.com/watch?v=XqH-EvHWXX0"
        },
        {
            "id": 111,
            "waza":"ジャグ一周",
            "favoriteSum":0,
            "level":4,
            "makeSum":0,
            "url":"https://www.youtube.com/watch?v=SbnWB24_PoQ"
        },
        {
            "id": 112,
            "waza":"剣先すべり〜中皿〜けん",
            "favoriteSum":0,
            "level":1,
            "makeSum":0,
            "url":"https://www.youtube.com/watch?v=6yCnul-OCzo"
        },
        {
            "id": 113,
            "waza":"一回転灯台〜フラミンゴ〜天中",
            "favoriteSum":0,
            "level":4,
            "makeSum":0,
            "url":"https://www.youtube.com/watch?v=tKFiD2aSLXg"
        },
        {
            "id": 114,
            "waza":"1回転Tapイン〜1.5ジャグけん〜フリップフリップ",
            "favoriteSum":0,
            "level":5,
            "makeSum":0,
            "url":"https://www.youtube.com/watch?v=bfOkySZgzWg"
        },
        {
            "id": 115,
            "waza":"ヨーロッパ一周",
            "favoriteSum":0,
            "level":2,
            "makeSum":0,
            "url":"https://www.youtube.com/watch?v=TG_o1lPSD_U"
        },
        {
            "id": 116,
            "waza":"半遊泳〜トス〜螺旋飛行機",
            "favoriteSum":0,
            "level":4,
            "makeSum":0,
            "url":"https://www.youtube.com/watch?v=1-lBS1rvepU"
        },
        {
            "id": 117,
            "waza":"フリップダウンスパイク〜１回転逆落とし",
            "favoriteSum":0,
            "level":4,
            "makeSum":0,
            "url":"https://www.youtube.com/watch?v=NmxDuzawOAI"
        },
        {
            "id": 118,
            "waza":"大皿〜両手ジャグ３回〜けん",
            "favoriteSum":0,
            "level":2,
            "makeSum":0,
            "url":"https://www.youtube.com/watch?v=hsDgMfSUa5g"
        },
        {
            "id": 119,
            "waza":"2回転飛行機〜インスタ中皿〜天中ファスト",
            "favoriteSum":0,
            "level":5,
            "makeSum":0,
            "url":"https://www.youtube.com/watch?v=YG_n28gXtHQ"
        },
        {
            "id": 120,
            "waza":"前振りろうそく〜ゴースト逆落とし〜3回転はねけん",
            "favoriteSum":0,
            "level":4,
            "makeSum":0,
            "url":"https://www.youtube.com/watch?v=d0p2x_3-18w"
        },
        {
            "id": 121,
            "waza":"ポップコーン〜アームバウンススパイク",
            "favoriteSum":0,
            "level":3,
            "makeSum":0,
            "url":"https://www.youtube.com/watch?v=Uyrcru_vbLw"
        },
        {
            "id": 122,
            "waza":"2回転持ち替えけん〜2回転風車",
            "favoriteSum":0,
            "level":5,
            "makeSum":0,
            "url":"https://www.youtube.com/watch?v=dAaJoboSvCs"
        },
        {
            "id": 123,
            "waza":"1回転竹馬〜まさかり〜逆落とし",
            "favoriteSum":0,
            "level":4,
            "makeSum":0,
            "url":"https://www.youtube.com/watch?v=hQ-Wowq3klY"
        },
        {
            "id": 124,
            "waza":"フリップ大皿〜ジャグ大皿〜フリップけん",
            "favoriteSum":0,
            "level":3,
            "makeSum":0,
            "url":"https://www.youtube.com/watch?v=IDqa9WUI-Sg"
        },
        {
            "id": 125,
            "waza":"ふりけん〜持ち替え〜はねけん～持ち替え～地球回し",
            "favoriteSum":0,
            "level":2,
            "makeSum":0,
            "url":"https://www.youtube.com/watch?v=6yEqi7OdGN0"
        },
        {
            "id": 126,
            "waza":"中百舌鳥一周",
            "favoriteSum":0,
            "level":3,
            "makeSum":0,
            "url":"https://www.youtube.com/watch?v=zY-bTfggWGs"
        },
        {
            "id": 127,
            "waza":"1回転持ち替えけん〜中皿〜灯立〜持ち替えけん",
            "favoriteSum":0,
            "level":4,
            "makeSum":0,
            "url":"https://www.youtube.com/watch?v=6HBZMGNMcl0"
        },
        {
            "id": 128,
            "waza":"Sweets(天中)〜スクリュー",
            "favoriteSum":0,
            "level":4,
            "makeSum":0,
            "url":"https://www.youtube.com/watch?v=WdNCKQzxDiw"
        },
        {
            "id": 129,
            "waza":"こっくり一周〜居合けん",
            "favoriteSum":0,
            "level":4,
            "makeSum":0,
            "url":"https://www.youtube.com/watch?v=gNmXKUspdYs"
        },
        {
            "id": 130,
            "waza":"シートノック〜ムーンサルト〜サイドスパイク",
            "favoriteSum":0,
            "level":2,
            "makeSum":0,
            "url":"https://www.youtube.com/watch?v=svd5d5fs7yk"
        },
        {
            "id": 131,
            "waza":"大皿遠心力裏月〜押し付け小皿〜逆落とし",
            "favoriteSum":0,
            "level":3,
            "makeSum":0,
            "url":"https://www.youtube.com/watch?v=B0YDFC77PVk"
        },
        {
            "id": 132,
            "waza":"中皿〜フリップ中皿〜ガンスリンガー中皿〜天中ファスト",
            "favoriteSum":0,
            "level":2,
            "makeSum":0,
            "url":"https://www.youtube.com/watch?v=5XzyexBe314"
        },
        {
            "id": 133,
            "waza":"振りペンギン中皿〜灯台〜持ち替えけん",
            "favoriteSum":0,
            "level":3,
            "makeSum":0,
            "url":"https://www.youtube.com/watch?v=vKSzkoOJK0Q"
        },
        {
            "id": 134,
            "waza":"一回転tapイン〜tapイン〜はねけん（1.5tapイン）",
            "favoriteSum":0,
            "level":4,
            "makeSum":0,
            "url":"https://www.youtube.com/watch?v=X3UAlFvMLrk"
        },
        {
            "id": 135,
            "waza":"一回転灯台インスタけん〜中皿〜一回転灯台インスタ天中",
            "favoriteSum":0,
            "level":4,
            "makeSum":0,
            "url":"https://www.youtube.com/watch?v=B6zuFNSx50o"
        },
        {
            "id": 136,
            "waza":"すくいけん〜持ち替え地球回し〜0.5スワップ逆落とし",
            "favoriteSum":0,
            "level":3,
            "makeSum":0,
            "url":"https://www.youtube.com/watch?v=urp6wdsAJtM"
        },
        {
            "id": 137,
            "waza":"風車ふりけん〜中皿〜スイベル中皿〜天中",
            "favoriteSum":0,
            "level":2,
            "makeSum":0,
            "url":"https://www.youtube.com/watch?v=ni4SgGSAEoY"
        },
        {
            "id": 138,
            "waza":"宇宙一周〜地球回し",
            "favoriteSum":0,
            "level":2,
            "makeSum":0,
            "url":"https://www.youtube.com/watch?v=FVwHa819a6g"
        },
        {
            "id": 139,
            "waza":"うぐいす〜谷渡り〜持ち替え中皿〜天中",
            "favoriteSum":0,
            "level":2,
            "makeSum":0,
            "url":"https://www.youtube.com/watch?v=7SWHnZJDFg8"
        },
        {
            "id": 140,
            "waza":"1回転灯台インスタろうそく〜ゴースト逆落とし",
            "favoriteSum":0,
            "level":4,
            "makeSum":0,
            "url":"https://www.youtube.com/watch?v=HAOtL3JoFWU"
        },
        {
            "id": 141,
            "waza":"アンダーバード〜えび反り〜けん",
            "favoriteSum":0,
            "level":3,
            "makeSum":0,
            "url":"https://www.youtube.com/watch?v=EQOmePK9Yfs"
        },
        {
            "id": 142,
            "waza":"ポッキー",
            "favoriteSum":0,
            "level":1,
            "makeSum":0,
            "url":"https://www.youtube.com/watch?v=sOWBCSbGp3c"
        },
        {
            "id": 143,
            "waza":"タモツチャンス",
            "favoriteSum":0,
            "level":5,
            "makeSum":0,
            "url":"https://www.youtube.com/watch?v=tY1z_aJlwrw"
        },
        {
            "id": 144,
            "waza":"スクランブル飛行機〜バックスルー持ち替え〜地球回し",
            "favoriteSum":0,
            "level":2,
            "makeSum":0,
            "url":"https://www.youtube.com/watch?v=CQOUOUwRiAM"
        },
        {
            "id": 145,
            "waza":"裏月面〜ブレス〜天中",
            "favoriteSum":0,
            "level":4,
            "makeSum":0,
            "url":"https://www.youtube.com/watch?v=iwWaetVGur8"
        },
        {
            "id": 146,
            "waza":"飛行機〜はねけん〜遠心力逆落とし",
            "favoriteSum":0,
            "level":3,
            "makeSum":0,
            "url":"https://www.youtube.com/watch?v=BSjgLb7SSTA"
        },
        {
            "id": 147,
            "waza":"すくいけん〜裏倒立〜ペンギン逆落とし",
            "favoriteSum":0,
            "level":4,
            "makeSum":0,
            "url":"https://www.youtube.com/watch?v=RI01wWIylfU"
        },
        {
            "id": 148,
            "waza":"大皿横バィーン大皿〜ハーフフリップ持ち替え小皿〜前うち〜中皿〜持ち替え中皿〜天中",
            "favoriteSum":0,
            "level":2,
            "makeSum":0,
            "url":"https://www.youtube.com/watch?v=i4o1pjgR7Zw"
        },
        {
            "id": 149,
            "waza":"しまいけん",
            "favoriteSum":0,
            "level":1,
            "makeSum":0,
            "url":"https://www.youtube.com/watch?v=dQk-rbYz3Cg"
        },
        {
            "id": 150,
            "waza":"裏竹馬〜まさかり〜けん",
            "favoriteSum":0,
            "level":3,
            "makeSum":0,
            "url":"https://www.youtube.com/watch?v=0N3P7vGqBtk"
        },
        {
            "id": 151,
            "waza":"風車うぐいす〜天中",
            "favoriteSum":0,
            "level":3,
            "makeSum":0,
            "url":"https://www.youtube.com/watch?v=rkOj-AS9WA0"
        },
        {
            "id": 152,
            "waza":"裏どじょうすくい〜遠心力〜お年玉",
            "favoriteSum":0,
            "level":1,
            "makeSum":0,
            "url":"https://www.youtube.com/watch?v=Lep6VLgb3kc"
        },
        {
            "id": 153,
            "waza":"フリップ灯台〜裏一回転フリップ灯台〜もちかえけん",
            "favoriteSum":0,
            "level":5,
            "makeSum":0,
            "url":"https://www.youtube.com/watch?v=qy59R5vq7hU"
        },
        {
            "id": 154,
            "waza":"1回転飛行機〜UFO〜1.5とめけん",
            "favoriteSum":0,
            "level":3,
            "makeSum":0,
            "url":"https://www.youtube.com/watch?v=NOwkxAUGqJ8"
        },
        {
            "id": 155,
            "waza":"とめけん〜Hand Toss",
            "favoriteSum":0,
            "level":1,
            "makeSum":0,
            "url":"https://www.youtube.com/watch?v=p5-p6uP_RzI"
        },
        {
            "id": 156,
            "waza":"裏月〜倒立〜裏1回転裏月〜裏逆落とし",
            "favoriteSum":0,
            "level":4,
            "makeSum":0,
            "url":"https://www.youtube.com/watch?v=pDdz3yGfxcY"
        },
        {
            "id": 157,
            "waza":"うぐいす〜てんとう虫〜小指姫",
            "favoriteSum":0,
            "level":2,
            "makeSum":0,
            "url":"https://www.youtube.com/watch?v=f2BhDVMudZI"
        },
        {
            "id": 158,
            "waza":"ターンブリッジ",
            "favoriteSum":0,
            "level":2,
            "makeSum":0,
            "url":"https://www.youtube.com/watch?v=cUB6wRTfjRs"
        },
        {
            "id": 159,
            "waza":"1回転灯台〜タップとんぼ返りインスタけん",
            "favoriteSum":0,
            "level":4,
            "makeSum":0,
            "url":"https://www.youtube.com/watch?v=WR-P4APyhHE"
        },
        {
            "id": 160,
            "waza":"中皿～月面～１回転逆落とし",
            "favoriteSum":0,
            "level":2,
            "makeSum":0,
            "url":"https://www.youtube.com/watch?v=U8l5OXvQrgk"
        },
        {
            "id": 161,
            "waza":"風車天中〜ガンマン〜地獄回し",
            "favoriteSum":0,
            "level":4,
            "makeSum":0,
            "url":"https://www.youtube.com/watch?v=3f3cj5_hwps"
        },
        {
            "id": 162,
            "waza":"中皿〜大皿〜サイドスパイク〜サイドスパイク",
            "favoriteSum":0,
            "level":2,
            "makeSum":0,
            "url":"https://www.youtube.com/watch?v=sTzs6m2AvmI"
        },
        {
            "id": 163,
            "waza":"ジャグ〜２回転ジャグ〜フリップ灯台〜２回転ジャグ〜ジャグけん",
            "favoriteSum":0,
            "level":5,
            "makeSum":0,
            "url":"https://www.youtube.com/watch?v=eH4tGqCEevM"
        },
        {
            "id": 164,
            "waza":"裏ふりろうそく〜フリップ逆落とし",
            "favoriteSum":0,
            "level":2,
            "makeSum":0,
            "url":"https://www.youtube.com/watch?v=IQozVB9yQdE"
        },
        {
            "id": 165,
            "waza":"エレベーター～つるし持ち～手の甲招き猫～すくい持ち替え",
            "favoriteSum":0,
            "level":2,
            "makeSum":0,
            "url":"https://www.youtube.com/watch?v=GkHOwkEXPbo"
        },
        {
            "id": 166,
            "waza":"一回転ブリッジ～回転けん～地球回し",
            "favoriteSum":0,
            "level":3,
            "makeSum":0,
            "url":"https://www.youtube.com/watch?v=RK1n-lBAWTo"
        },
        {
            "id": 167,
            "waza":"裏月面～トレフリップ～逆落とし",
            "favoriteSum":0,
            "level":5,
            "makeSum":0,
            "url":"https://www.youtube.com/watch?v=NZg9_sxb1hw"
        },
        {
            "id": 168,
            "waza":"ぺんぎん中皿～大皿～つばめ返し～けん",
            "favoriteSum":0,
            "level":1,
            "makeSum":0,
            "url":"https://www.youtube.com/watch?v=Opnt2BiC8k8"
        },
        {
            "id": 169,
            "waza":"竹馬～灯台インスタ竹馬～天中殺",
            "favoriteSum":0,
            "level":4,
            "makeSum":0,
            "url":"https://www.youtube.com/watch?v=jpPR_YiqmIk"
        },
        {
            "id": 170,
            "waza":"ジャグ大皿～バーティカルターンテーブル～けん",
            "favoriteSum":0,
            "level":3,
            "makeSum":0,
            "url":"https://www.youtube.com/watch?v=geJ4naR-zAM"
        },
        {
            "id": 171,
            "waza":"大皿～リフティング大皿～けん",
            "favoriteSum":0,
            "level":1,
            "makeSum":0,
            "url":"https://www.youtube.com/watch?v=IiDzsrZWw7s"
        },
        {
            "id": 172,
            "waza":"飛行機～ブリッジ～スイッチ逆落とし",
            "favoriteSum":0,
            "level":2,
            "makeSum":0,
            "url":"https://www.youtube.com/watch?v=iQINGj_rFh4"
        },
        {
            "id": 173,
            "waza":"すくいけんファストハンド～フリップジャグけん",
            "favoriteSum":0,
            "level":3,
            "makeSum":0,
            "url":"https://www.youtube.com/watch?v=QQT18N1OTmA"
        },
        {
            "id": 174,
            "waza":"ろうそく～倒立(補助付き)～逆落とし(補助付き)",
            "favoriteSum":0,
            "level":1,
            "makeSum":0,
            "url":"https://www.youtube.com/watch?v=CbYJ6hOT6cU"
        },
        {
            "id": 175,
            "waza":"うぐいすの地獄めぐり",
            "favoriteSum":0,
            "level":5,
            "makeSum":0,
            "url":"https://www.youtube.com/watch?v=7dRgA7aiuFQ"
        },
        {
            "id": 176,
            "waza":"ふりけん～竹とんぼスイベルペンギンけん",
            "favoriteSum":0,
            "level":2,
            "makeSum":0,
            "url":"https://www.youtube.com/watch?v=DjtXrF9XZPg"
        },
        {
            "id": 177,
            "waza":"スイーツスペシャル月面～すくいけん",
            "favoriteSum":0,
            "level":3,
            "makeSum":0,
            "url":"https://www.youtube.com/watch?v=98wMfjslXBI"
        },
        {
            "id": 178,
            "waza":"天中～灯立～天中",
            "favoriteSum":0,
            "level":3,
            "makeSum":0,
            "url":"https://www.youtube.com/watch?v=a6re-AIzb-I"
        },
        {
            "id": 179,
            "waza":"一回転飛行機～持ち替え～サイクロン",
            "favoriteSum":0,
            "level":3,
            "makeSum":0,
            "url":"https://www.youtube.com/watch?v=9o8E4vS7nQQ"
        },
        {
            "id": 180,
            "waza":"大皿～ハーフフリップ～ハーフターンテーブル～けん",
            "favoriteSum":0,
            "level":2,
            "makeSum":0,
            "url":"https://www.youtube.com/watch?v=nHKM8NfxgYU"
        },
        {
            "id": 181,
            "waza":"３タップ～２ジャグ～フリップタップイン",
            "favoriteSum":0,
            "level":5,
            "makeSum":0,
            "url":"https://www.youtube.com/watch?v=tVSnV8l3u-k"
        },
        {
            "id": 182,
            "waza":"ジャグ大皿～持ち替え中皿～天中殺",
            "favoriteSum":0,
            "level":2,
            "makeSum":0,
            "url":"https://www.youtube.com/watch?v=jKTe7LX8WHU"
        },
        {
            "id": 183,
            "waza":"ディケイド一周",
            "favoriteSum":0,
            "level":3,
            "makeSum":0,
            "url":"https://www.youtube.com/watch?v=qMF_JglRxdE"
        },
        {
            "id": 184,
            "waza":"大皿～アームバランス～中皿～天中",
            "favoriteSum":0,
            "level":2,
            "makeSum":0,
            "url":"https://www.youtube.com/watch?v=bmEkgUGDnIk"
        },
        {
            "id": 185,
            "waza":"フリップジャグゴースト灯台～裏とんぼインスタ一回転逆落とし",
            "favoriteSum":0,
            "level":5,
            "makeSum":0,
            "url":"https://www.youtube.com/watch?v=JxzDCvm0QZU"
        },
        {
            "id": 186,
            "waza":"前振り小皿うぐいす～回転谷渡り～けんファスト",
            "favoriteSum":0,
            "level":3,
            "makeSum":0,
            "url":"https://www.youtube.com/watch?v=ptp2AvsNbqI"
        },
        {
            "id": 187,
            "waza":"トス～ぬんちゃく一回転とめけん",
            "favoriteSum":0,
            "level":3,
            "makeSum":0,
            "url":"https://www.youtube.com/watch?v=6FQGQMfQOis"
        },
        {
            "id": 188,
            "waza":"おみこし～ヘリコプター～中皿～天中",
            "favoriteSum":0,
            "level":3,
            "makeSum":0,
            "url":"https://www.youtube.com/watch?v=lu84RcgP_X0"
        },
        {
            "id": 189,
            "waza":"とめけん～コマ～忍び落とし",
            "favoriteSum":0,
            "level":1,
            "makeSum":0,
            "url":"https://www.youtube.com/watch?v=V8yVgJYTGto"
        },
        {
            "id": 190,
            "waza":"天中うぐいす～天中～地獄回し",
            "favoriteSum":0,
            "level":3,
            "makeSum":0,
            "url":"https://www.youtube.com/watch?v=kWwQTjz6kqU"
        },
        {
            "id": 191,
            "waza":"大皿～土星～けん",
            "favoriteSum":0,
            "level":1,
            "makeSum":0,
            "url":"https://www.youtube.com/watch?v=Xomjh9VL9mg"
        },
        {
            "id": 192,
            "waza":"1回転裏月～バックフリップ～1回転tapイン",
            "favoriteSum":0,
            "level":5,
            "makeSum":0,
            "url":"https://www.youtube.com/watch?v=ZqdgtsDROKs"
        },
        {
            "id": 193,
            "waza":"すくいけん～無回転月面～すくいけ",
            "favoriteSum":0,
            "level":3,
            "makeSum":0,
            "url":"https://www.youtube.com/watch?v=MPvbiIfx-zM"
        },
        {
            "id": 194,
            "waza":"つるし逆落とし～はやて中皿～逆落とし",
            "favoriteSum":0,
            "level":2,
            "makeSum":0,
            "url":"https://www.youtube.com/watch?v=tiN-LT45JCs"
        },
        {
            "id": 195,
            "waza":"すくいけん～飛龍のぼり～はねけん",
            "favoriteSum":0,
            "level":2,
            "makeSum":0,
            "url":"https://www.youtube.com/watch?v=xmiMzTHB54w"
        },
        {
            "id": 196,
            "waza":"フリフリ灯台～フリップけん",
            "favoriteSum":0,
            "level":4,
            "makeSum":0,
            "url":"https://www.youtube.com/watch?v=3oVP78-AFPI"
        },
        {
            "id": 197,
            "waza":"まわしけん～ダマスピン",
            "favoriteSum":0,
            "level":1,
            "makeSum":0,
            "url":"https://www.youtube.com/watch?v=F1KhSYvEhkY"
        },
        {
            "id": 198,
            "waza":"前振りろうそく→フリップ灯台→ろうそく返し",
            "favoriteSum":0,
            "level":4,
            "makeSum":0,
            "url":"https://www.youtube.com/watch?v=6vpG78CQV50"
        },
        {
            "id": 199,
            "waza":"大皿～中皿～遠心力ぺんぎん中皿～持ち替え天中",
            "favoriteSum":0,
            "level":2,
            "makeSum":0,
            "url":"https://www.youtube.com/watch?v=1B8r8ec1hE4"
        },
        {
            "id": 200,
            "waza":"天中ファスト～倒立～すくいけんファスト～地球回しファスト",
            "favoriteSum":0,
            "level":5,
            "makeSum":0,
            "url":"https://www.youtube.com/watch?v=Yf5rqTR5eXE"
        },
        {
            "id": 201,
            "waza":"ふりけん～持ち替え～はねけん～持ち替え～地球回し～持ち替え～裏はねけん～持ち替え～ワールウィンド",
            "favoriteSum":0,
            "level":3,
            "makeSum":0,
            "url":"https://www.youtube.com/watch?v=uPMIcHVp_pA"
        },
        {
            "id": 202,
            "waza":"裏月面～小皿月面～ハーフバレル～逆落としファスト",
            "favoriteSum":0,
            "level":4,
            "makeSum":0,
            "url":"https://www.youtube.com/watch?v=6YKzWrDyWsA"
        },
        {
            "id": 203,
            "waza":"スイベル持ち替えけん～ワールウィンド",
            "favoriteSum":0,
            "level":3,
            "makeSum":0,
            "url":"https://www.youtube.com/watch?v=Z4ygmY3yjaM"
        },
        {
            "id": 204,
            "waza":"1回転タップクッション灯台～インスタ天中",
            "favoriteSum":0,
            "level":4,
            "makeSum":0,
            "url":"https://www.youtube.com/watch?v=QWHBpF0FKmU"
        },
        {
            "id": 205,
            "waza":"風車とめけん～回転うぐいす～ジャグけん",
            "favoriteSum":0,
            "level":3,
            "makeSum":0,
            "url":"https://www.youtube.com/watch?v=OzfQVo-YruE"
        },
        {
            "id": 206,
            "waza":"大皿~飛龍上り~遠心力裏月~ペンギン逆落とし",
            "favoriteSum":0,
            "level":3,
            "makeSum":0,
            "url":"https://www.youtube.com/watch?v=FzEulMtjlYg"
        },
        {
            "id": 207,
            "waza":"1回転飛行機~はねけん~インスタ1回転持ち替えけん",
            "favoriteSum":0,
            "level":4,
            "makeSum":0,
            "url":"https://www.youtube.com/watch?v=jOR94_a5Nzc"
        },
        {
            "id": 208,
            "waza":"おとしだま~たけとんぼ~地球回し",
            "favoriteSum":0,
            "level":1,
            "makeSum":0,
            "url":"https://www.youtube.com/watch?v=P02mXqzBw-E"
        },
        {
            "id": 209,
            "waza":"1回転飛行機~持ち替え~フィンガースピン",
            "favoriteSum":0,
            "level":2,
            "makeSum":0,
            "url":"https://www.youtube.com/watch?v=S-WQ5fleJlc"
        },
        {
            "id": 210,
            "waza":"スワップ逆落とし~持ち替え~スワップ逆落とし",
            "favoriteSum":0,
            "level":3,
            "makeSum":0,
            "url":"https://www.youtube.com/watch?v=SBIMrr4FUjQ"
        },
        {
            "id": 211,
            "waza":"2回転灯台~ひねり裏月~バックフリップ~裏逆落とし",
            "favoriteSum":0,
            "level":5,
            "makeSum":0,
            "url":"https://www.youtube.com/watch?v=04bnlLwPQ9Y"
        },
        {
            "id": 212,
            "waza":"フィンガースピン灯台~ジャグけん",
            "favoriteSum":0,
            "level":4,
            "makeSum":0,
            "url":"https://www.youtube.com/watch?v=9tRF1MoN6Jc"
        }
    ]
}